ps4debug/__init__.py
ps4debug/commands.py
ps4debug/core.py
ps4debug/exceptions.py
ps4debug-0.1.6.dist-info/LICENSE
ps4debug-0.1.6.dist-info/METADATA
ps4debug-0.1.6.dist-info/WHEEL
ps4debug-0.1.6.dist-info/top_level.txt
ps4debug-0.1.6.dist-info/RECORD
