Metadata-Version: 2.1
Name: ps4debug
Version: 0.1.6
Summary: Asynchronous ps4debug implementation in python
Home-page: https://github.com/Jay184/PyPS4debug
Author: Jay
Author-email: 0jaybae0@gmail.com
Project-URL: Bug Tracker, https://github.com/Jay184/PyPS4debug/issues
Classifier: Programming Language :: Python :: 3
Classifier: Operating System :: OS Independent
Requires-Python: >=3.10
License-File: LICENSE
Requires-Dist: construct
